hiveplot/__init__.py
hiveplot/hiveplot.py
hiveplot/test_hiveplot.py
hiveplot-2017.10.17.21.7.dist-info/DESCRIPTION.rst
hiveplot-2017.10.17.21.7.dist-info/METADATA
hiveplot-2017.10.17.21.7.dist-info/RECORD
hiveplot-2017.10.17.21.7.dist-info/WHEEL
hiveplot-2017.10.17.21.7.dist-info/metadata.json
hiveplot-2017.10.17.21.7.dist-info/top_level.txt
