Metadata-Version: 2.0
Name: hiveplot
Version: 2017.10.17.21.7
Summary: Hive plots in Python!
Home-page: https://github.com/ericmjl/hiveplot
Author: Eric J. Ma
Author-email: ericmajinglong@gmail.com
License: MIT
Keywords: network visualization,matplotlib,hiveplot
Platform: UNKNOWN
Classifier: Topic :: Scientific/Engineering :: Visualization
Requires-Dist: matplotlib (>=2.0.0)
Requires-Dist: pycodestyle (==2.3.1)
